ktxo/scraper/__init__.py
ktxo/scraper/_about.py
ktxo/scraper/base_scraper.py
base_scraper-1.0.2.dist-info/METADATA
base_scraper-1.0.2.dist-info/WHEEL
base_scraper-1.0.2.dist-info/top_level.txt
base_scraper-1.0.2.dist-info/RECORD
